<layer>
  <name>nhdflowline</name>
  <id>LayerInfoImpl--1bc55906:130729d4f6a:-7ffc</id>
  <type>VECTOR</type>
  <defaultStyle>
    <id>StyleInfoImpl--6a5a06df:13109f6b21d:-7ffd</id>
  </defaultStyle>
  <resource class="featureType">
    <id>FeatureTypeInfoImpl--1bc55906:130729d4f6a:-7ffd</id>
  </resource>
  <enabled>true</enabled>
  <metadata>
    <entry key="GWC.autoCacheStyles">true</entry>
    <entry key="GWC.metaTilingX">4</entry>
    <entry key="GWC.metaTilingY">4</entry>
    <entry key="GWC.gutter">0</entry>
    <entry key="GWC.enabled">true</entry>
    <entry key="GWC.cacheFormats">image/jpeg,image/png</entry>
    <entry key="GWC.gridSets">EPSG:4326,EPSG:900913</entry>
  </metadata>
  <attribution>
    <logoWidth>0</logoWidth>
    <logoHeight>0</logoHeight>
  </attribution>
</layer>